mpl3d_turbo-0.1.0.dist-info/METADATA
mpl3d_turbo-0.1.0.dist-info/WHEEL
mpl3d_turbo/py_fallback.py
mpl3d_turbo/__init__.py
mpl3d_turbo/mpl3d_turbo.cp311-win_amd64.pyd
mpl3d_turbo-0.1.0.dist-info/RECORD
