Metadata-Version: 2.4
Name: mpl3d-turbo
Version: 0.1.0
Classifier: Programming Language :: Python :: 3
Classifier: Programming Language :: Python :: 3.8
Classifier: Programming Language :: Python :: 3.9
Classifier: Programming Language :: Python :: 3.10
Classifier: Programming Language :: Python :: 3.11
Classifier: Programming Language :: Python :: 3.12
Classifier: Programming Language :: Python :: 3.13
Classifier: Programming Language :: Rust
Classifier: License :: OSI Approved :: MIT License
Classifier: Operating System :: OS Independent
Classifier: Topic :: Scientific/Engineering :: Visualization
Requires-Dist: numpy>=1.20.0
Requires-Dist: matplotlib>=3.5.0
Summary: High-performance Matplotlib 3D plotting library implemented in Rust
Keywords: matplotlib,3d,rust,pde,visualization
Author-email: Steven Chen <i@stevenchen.site>
License: MIT
Requires-Python: >=3.8
